aliro_quantum/__init__.py
aliro_quantum/api_client.py
aliro_quantum/configuration.py
aliro_quantum/exceptions.py
aliro_quantum/rest.py
aliro_quantum/api/__init__.py
aliro_quantum/api/authentication_api.py
aliro_quantum/api/circuit_api.py
aliro_quantum/api/credentials_api.py
aliro_quantum/api/device_rankings_api.py
aliro_quantum/api/info_api.py
aliro_quantum/api/jobs_api.py
aliro_quantum/api/submissions_api.py
aliro_quantum/api/user_api.py
aliro_quantum/models/__init__.py
aliro_quantum/models/allocation.py
aliro_quantum/models/api_key.py
aliro_quantum/models/api_key_response.py
aliro_quantum/models/basic_success.py
aliro_quantum/models/change_password_parameters.py
aliro_quantum/models/circuit.py
aliro_quantum/models/compilation_parameters.py
aliro_quantum/models/control_flow_graph_circuit.py
aliro_quantum/models/credentials_add_parameters.py
aliro_quantum/models/credentials_aqt.py
aliro_quantum/models/credentials_basic.py
aliro_quantum/models/credentials_delete_parameters.py
aliro_quantum/models/credentials_honeywell.py
aliro_quantum/models/credentials_ibm.py
aliro_quantum/models/credentials_ibm_provider.py
aliro_quantum/models/credentials_rigetti.py
aliro_quantum/models/credentials_vendor.py
aliro_quantum/models/delete_submission_parameters.py
aliro_quantum/models/device_details.py
aliro_quantum/models/device_details_gate_info.py
aliro_quantum/models/device_details_gate_info_averages.py
aliro_quantum/models/device_list_response.py
aliro_quantum/models/device_ranking.py
aliro_quantum/models/device_ranking_response.py
aliro_quantum/models/device_ranking_response_recommendations.py
aliro_quantum/models/device_rankings_parameters.py
aliro_quantum/models/device_vendor_response.py
aliro_quantum/models/execution_parameters.py
aliro_quantum/models/execution_results.py
aliro_quantum/models/gate.py
aliro_quantum/models/info_get_response.py
aliro_quantum/models/info_get_response_data.py
aliro_quantum/models/job.py
aliro_quantum/models/job_allocations.py
aliro_quantum-2.33.0.dist-info/METADATA
aliro_quantum-2.33.0.dist-info/WHEEL
aliro_quantum-2.33.0.dist-info/top_level.txt
aliro_quantum-2.33.0.dist-info/RECORD
