Metadata-Version: 2.1
Name: aliro-quantum
Version: 2.33.0
Summary: Aliro Quantum App
Home-page: UNKNOWN
Author: OpenAPI Generator community
Author-email: nick@aliroquantum.com
License: UNKNOWN
Keywords: OpenAPI,OpenAPI-Generator,Aliro Quantum App
Platform: UNKNOWN
Requires-Dist: certifi
Requires-Dist: python-dateutil
Requires-Dist: six (>=1.10)
Requires-Dist: sseclient-py (>=1.7)
Requires-Dist: urllib3 (>=1.15)
